odoo8_addon_event_registration_seat_limit-8.0.4.0.0.99.dev8-py2.7-nspkg.pth
odoo_addons/event_registration_seat_limit/models.py
odoo_addons/event_registration_seat_limit/__openerp__.py
odoo_addons/event_registration_seat_limit/__init__.py
odoo_addons/event_registration_seat_limit/exceptions.py
odoo_addons/event_registration_seat_limit/README.rst
odoo_addons/event_registration_seat_limit/i18n/es.po
odoo_addons/event_registration_seat_limit/views/event.xml
odoo_addons/event_registration_seat_limit/tests/test_limits.py
odoo_addons/event_registration_seat_limit/tests/__init__.py
odoo_addons/event_registration_seat_limit/static/description/icon.svg
odoo_addons/event_registration_seat_limit/static/description/icon.png
odoo8_addon_event_registration_seat_limit-8.0.4.0.0.99.dev8.dist-info/top_level.txt
odoo8_addon_event_registration_seat_limit-8.0.4.0.0.99.dev8.dist-info/WHEEL
odoo8_addon_event_registration_seat_limit-8.0.4.0.0.99.dev8.dist-info/RECORD
odoo8_addon_event_registration_seat_limit-8.0.4.0.0.99.dev8.dist-info/metadata.json
odoo8_addon_event_registration_seat_limit-8.0.4.0.0.99.dev8.dist-info/DESCRIPTION.rst
odoo8_addon_event_registration_seat_limit-8.0.4.0.0.99.dev8.dist-info/METADATA
odoo8_addon_event_registration_seat_limit-8.0.4.0.0.99.dev8.dist-info/namespace_packages.txt
